<?xml version="1.0" encoding="UTF-8"?>
<office:document-meta xmlns:office="urn:oasis:names:tc:opendocument:xmlns:office:1.0" xmlns:xlink="http://www.w3.org/1999/xlink" xmlns:dc="http://purl.org/dc/elements/1.1/" xmlns:meta="urn:oasis:names:tc:opendocument:xmlns:meta:1.0" xmlns:ooo="http://openoffice.org/2004/office" xmlns:grddl="http://www.w3.org/2003/g/data-view#" office:version="1.2"><office:meta><meta:creation-date>2015-01-23T11:45:18.519136000</meta:creation-date><meta:generator>LibreOffice/4.3.3.2$Linux_X86_64 LibreOffice_project/430m0$Build-2</meta:generator><dc:date>2015-02-20T21:11:20.055570172</dc:date><meta:editing-duration>PT10M12S</meta:editing-duration><meta:editing-cycles>4</meta:editing-cycles><meta:document-statistic meta:table-count="1" meta:cell-count="0" meta:object-count="0"/></office:meta></office:document-meta>